{"trial_id": "082", "hyperparameters": {"space": [{"class_name": "Int", "config": {"name": "units_1", "default": null, "conditions": [], "min_value": 32, "max_value": 512, "step": 32, "sampling": "linear"}}, {"class_name": "Choice", "config": {"name": "activation", "default": "relu", "conditions": [], "values": ["relu", "tanh", "sigmoid"], "ordered": false}}, {"class_name": "Boolean", "config": {"name": "dropout_1", "default": false, "conditions": []}}, {"class_name": "Int", "config": {"name": "units_2", "default": null, "conditions": [], "min_value": 16, "max_value": 256, "step": 16, "sampling": "linear"}}, {"class_name": "Boolean", "config": {"name": "dropout_2", "default": false, "conditions": []}}], "values": {"units_1": 96, "activation": "tanh", "dropout_1": false, "units_2": 128, "dropout_2": false}}, "metrics": {"metrics": {"accuracy": {"direction": "max", "observations": [{"value": [0.7676911950111389], "step": 44}]}, "loss": {"direction": "min", "observations": [{"value": [0.41705721616744995], "step": 44}]}, "val_accuracy": {"direction": "max", "observations": [{"value": [0.7423343658447266], "step": 44}]}, "val_loss": {"direction": "min", "observations": [{"value": [0.4531308710575104], "step": 44}]}}}, "score": 0.7423343658447266, "best_step": 44, "status": "COMPLETED", "message": null}